{"./":{"url":"./","title":"简介","keywords":"","body":"1. 哈工大《离散数学引论》课本习题答案补充1.1. 前言1.2. 在线阅读地址1.3. 贡献规则1.3.1. 先决条件1.3.2. 参考答案格式1.3.3. 错误解析反馈1. 哈工大《离散数学引论》课本习题答案补充 1.1. 前言 《离散数学引论》是哈尔滨工业大学大一课程 集合论和图论(HIT-CS31107) 的配套教材。 考虑到此教材出版时间久远，内容更新缓慢，尤其是课后习题部分错漏部分迟迟不做出修订，部分题目官方也未曾提供参考答案，因此有理由相信，不只是我们对一份完整而正确的《离散数学引论》课后习题参考答案存在需求。这也是创立本项目的原因。 本人将在此不定期上传对于本人来说难或不难、会写或不会写，但在官方提供的参考答案中存在错误、或未提供参考答案的题目及其非官方解析。 1.2. 在线阅读地址 我们提供了在线阅读电子书，现在你可以直接在这里阅读，祝你学习愉快。 源项目地址。 1.3. 贡献规则 我们非常欢迎PR 如果你认同项目创立者的观点，并希望贡献本项目，可以参考此处的贡献规则，贡献你的答案。 1.3.1. 先决条件 在贡献本项目之前，你需要会以下技能： Git Markdown LaTeX (KaTex) 1.3.2. 参考答案格式 核心内容在src内，目录树如下： ├─part-01-set-theory │ └─chapter-01 │ └─chapter-02 │ └─chapter-03 │ └─ ... └─part-02-graph-theory │ └─chapter-01 │ └─chapter-02 │ └─chapter-03 │ └─ ... 每道题的题号需要使用一个三级标题，以图论第六章6.3为例: --- page: P209 --- # 第六章 图的基本概念 ## 6.3 路、圈、连通图 ### 1. ... ### 2. ... ### 3. ... 1.3.3. 错误解析反馈 因为本人太菜了，贡献本项目的大佬们也可能存在疏漏，所以如果你在查看参考答案的过程中发现了纰漏，请提交issue，便于我们进行修正。 使用知识共享 署名-相同方式共享 4.0协议发布            updated 2021-06-11 00:48:31 "},"src/part-01-set-theory/chapter-02/2.3.html":{"url":"src/part-01-set-theory/chapter-02/2.3.html","title":"2.3 映射的一般性质","keywords":"","body":"1. 第二章 映射1.1. 2.3 映射的一般性质1.1.1. 10.1. 第二章 映射 1.1. 2.3 映射的一般性质 1.1.1. 10. 设 MMM 是一个非空集合， φ:M→M, N⊆M\\varphi : M \\rightarrow M ,\\ N \\subseteq Mφ:M→M, N⊆M 。令 &#x1D49C;={P ∣ P⊆M&#x1D49C; = \\{ P \\ | \\ P \\subseteq MA={P ∣ P⊆M 且 N⊆P, φ(P)⊆P}N \\subseteq P , \\ \\varphi(P) \\subseteq P \\}N⊆P, φ(P)⊆P} ， G=⋂P∈&#x1D49C;PG= \\displaystyle\\bigcap_{P \\in &#x1D49C;} PG=P∈A⋂​P 。 试证： G∈&#x1D49C;G \\in &#x1D49C;G∈A ； N⋃φ(G)=GN \\bigcup \\varphi (G) = GN⋃φ(G)=G 。 证明： ∀x∈G，P∈&#x1D49C;\\forall x \\in G ， P \\in &#x1D49C;∀x∈G，P∈A ，有 x∈Px \\in Px∈P 所以 ∀x∈G，x∈M\\forall x \\in G ， x \\in M∀x∈G，x∈M ，即 G⊆MG \\subseteq MG⊆M ∀x∈N，x∈P\\forall x \\in N ，x \\in P∀x∈N，x∈P ，即 x∈⋂P∈&#x1D49C;P=Gx \\in \\displaystyle\\bigcap_{P \\in &#x1D49C;} P = Gx∈P∈A⋂​P=G ，所以 N⊆GN \\subseteq GN⊆G ∀x∈G\\forall x \\in G∀x∈G ，有 φ(x)∈P\\varphi (x) \\in Pφ(x)∈P ，即 φ(x)∈⋂P∈&#x1D49C;P=G\\varphi (x) \\in \\displaystyle\\bigcap_{P \\in &#x1D49C;} P = Gφ(x)∈P∈A⋂​P=G ，所以 φ(G)⊆G\\varphi (G) \\subseteq Gφ(G)⊆G 综上 G∈&#x1D49C;G \\in &#x1D49C;G∈A 先证 N⋃φ(G)⊆GN \\bigcup \\varphi (G) \\subseteq GN⋃φ(G)⊆G 。 ∀x∈N⋃φ(G)\\forall x \\in N \\bigcup \\varphi (G)∀x∈N⋃φ(G) ， x∈N 或 x∈φ(G)x \\in N \\ 或 \\ x \\in \\varphi (G)x∈N 或 x∈φ(G) 若 x∈Nx \\in Nx∈N ，因为 N⊆GN \\subseteq GN⊆G ，所以 x∈Gx \\in Gx∈G 。 若 x∈φ(G)x \\in \\varphi (G)x∈φ(G) ，因为 φ(G)⊆G\\varphi (G) \\subseteq Gφ(G)⊆G ，所以 x∈Gx \\in Gx∈G 。 所以 N⋃φ(G)⊆GN \\bigcup \\varphi (G) \\subseteq GN⋃φ(G)⊆G 。 再证 G⊆N⋃φ(G)G \\subseteq N \\bigcup \\varphi (G)G⊆N⋃φ(G) ： ∀x∈G\\forall x \\in G∀x∈G ， 由于 N⊆GN \\subseteq GN⊆G ， 若 x∈Nx \\in Nx∈N , x∈N⋃φ(G)x \\in N \\bigcup \\varphi (G)x∈N⋃φ(G) 若 x∉Nx \\notin Nx∈/N , 则 x∈G\\Nx \\in G \\backslash Nx∈G\\N 下证： ∀x∈G\\N, φ(x)∉N\\forall x \\in G \\backslash N, \\ \\varphi (x) \\notin N∀x∈G\\N, φ(x)∈/N 。 假设 φ(x)∈N\\varphi (x) \\in Nφ(x)∈N ，那么 G\\x∈&#x1D49C;G \\backslash x \\in &#x1D49C;G\\x∈A ，与 G=⋂P∈&#x1D49C;PG= \\displaystyle\\bigcap_{P \\in &#x1D49C;} PG=P∈A⋂​P 矛盾。 故 ∀x∈G\\N, φ(x)∉N\\forall x \\in G \\backslash N, \\ \\varphi (x) \\notin N∀x∈G\\N, φ(x)∈/N 即 ∀x∈G\\N, φ(x)∈G\\N\\forall x \\in G \\backslash N, \\ \\varphi (x) \\in G \\backslash N∀x∈G\\N, φ(x)∈G\\N 再下证： φ:G\\N→G\\N\\varphi : G \\backslash N \\rightarrow G \\backslash Nφ:G\\N→G\\N 是双射。 假设 φ:G\\N→G\\N\\varphi : G \\backslash N \\rightarrow G \\backslash Nφ:G\\N→G\\N 不是满射， 即 ∃y∈G\\N, s.t. φ−1(y)=∅\\exist y \\in G \\backslash N , \\ s.t. \\ \\varphi ^{-1} (y) = \\empty∃y∈G\\N, s.t. φ−1(y)=∅ ， 那么 G\\y∈&#x1D49C;G \\backslash y \\in &#x1D49C;G\\y∈A ，与 G=⋂P∈&#x1D49C;PG= \\displaystyle\\bigcap_{P \\in &#x1D49C;} PG=P∈A⋂​P 矛盾。 所以 φ:G\\N→G\\N\\varphi : G \\backslash N \\rightarrow G \\backslash Nφ:G\\N→G\\N 是满射，也是双射。 即 φ(G\\N)=G\\N\\varphi (G \\backslash N) = G \\backslash Nφ(G\\N)=G\\N 所以 x∈G\\N=φ(G\\N)⊆φ(G)x \\in G \\backslash N = \\varphi (G \\backslash N) \\subseteq \\varphi (G)x∈G\\N=φ(G\\N)⊆φ(G) 。 使用知识共享 署名-相同方式共享 4.0协议发布            updated 2021-06-11 00:48:31 "},"src/part-02-graph-theory/chapter-06/6.3.html":{"url":"src/part-02-graph-theory/chapter-06/6.3.html","title":"6.3 路、圈、连通图","keywords":"","body":"1. 第六章 图的基本概念1.1. 6.3 路、圈、连通图1.1.1. 6.1.1.2. 10.1. 第六章 图的基本概念 1.1. 6.3 路、圈、连通图 1.1.1. 6. 在一个有 nnn 个人的宴会上，每个人至少有 mmm 个朋友 (2≤m≤n)(2 \\le m \\le n)(2≤m≤n) 。试证： 有不少于 m+1m+1m+1 个人，使得他们按某种方法坐在一张圆桌旁，每人的左、右均是他的朋友。 证明： 题目等价于证明：图 GGG 有 nnn 个顶点，当 δ(G)=m(2≤m≤n)\\delta (G) = m (2 \\le m \\le n)δ(G)=m(2≤m≤n) 时， GGG 存在长度至少为 m+1m + 1m+1 的圈。 设 GGG 的一条最长路为 v1v2…vpv_1 v_2 \\dots v_pv1​v2​…vp​ ，连接 v1v_1v1​ 的至少 mmm 个点必属于 {v2,v3,…,vp}\\{ v_2, v_3, \\dots , v_p \\}{v2​,v3​,…,vp​} ，否则此不为最长路，即 p≥m+1p \\ge m + 1p≥m+1 ，故 ∃i≥m+1, s,t. v1vi∈G\\exist i \\ge m + 1 , \\ s,t. \\ v_1 v_i \\in G∃i≥m+1, s,t. v1​vi​∈G ， v1v2…viv1v_1 v_2 \\dots v_i v_1v1​v2​…vi​v1​ 是 GGG 的一个长度至少为 m+1m + 1m+1 的圈。证毕。 1.1.2. 10. 设 GGG 是一个 (p,q)(p, q)(p,q) 图，证明： (a) 若 q≥pq \\ge pq≥p ，则 GGG 中有圈； (b) 若 q≥p+4q \\ge p + 4q≥p+4 ，则 GGG 包含两个边不重的圈。 证明： (a) (b) [证明 111 ] （此法被大佬锤了，因为要求是平面图，而欧拉定理是平面图的必要条件而非充分） 若 q≥p+4q \\ge p + 4q≥p+4 ，则 GGG 至少有五个圈（这五个圈不可分割成更小的圈）。 由四色定理，用四种颜色给这五个圈染色。存在一种染色方案，使得若两个圈有公共边，则染不同颜色。此方案下必存在两个圈颜色相同，即其不相邻，故没有重边。[证毕] 使用知识共享 署名-相同方式共享 4.0协议发布            updated 2021-06-11 00:48:31 "},"src/part-02-graph-theory/chapter-09/9.1.html":{"url":"src/part-02-graph-theory/chapter-09/9.1.html","title":"9.1 平面图及其欧拉公式","keywords":"","body":"1. 第九章 平面图及其着色1.1. 9.1 平面图及其欧拉公式1.1.1. 5.1. 第九章 平面图及其着色 1.1. 9.1 平面图及其欧拉公式 1.1.1. 5. 证明：不存在 777 条棱的多面体。 证明： 对于一个有 ppp 个顶点， qqq 条边， fff 个面的平面图， 易证不存在边数大于等于 444 的面，否则对于这样的面，其本身有至少 444 条棱，每个顶点与其他顶点相邻，至少有 888 条棱，与多面体有 777 条棱矛盾，故该多面体所有面边数都是 333 ，即 2q=3f2q = 3f2q=3f 。 由欧拉公式： p−q+f=2p - q + f = 2p−q+f=2 故 q=3p−6q = 3p - 6q=3p−6 。 代入 q=7q = 7q=7 解得 ppp 不是整数，故不存在这样的多面体。 使用知识共享 署名-相同方式共享 4.0协议发布            updated 2021-06-11 00:48:31 "},"src/part-02-graph-theory/chapter-09/9.3.html":{"url":"src/part-02-graph-theory/chapter-09/9.3.html","title":"9.3 库拉托斯基定理、对偶图","keywords":"","body":"1. 第九章 平面图及其着色1.1. 9.4 库拉托斯基定理、对偶图1.1.1. 21.1.2. 31. 第九章 平面图及其着色 1.1. 9.4 库拉托斯基定理、对偶图 1.1.1. 2 设 GGG 是平面图。证明： G∗∗G^{**}G∗∗ 同构于 GGG 当且仅当 GGG 是连通的。 1.1.2. 3 若一个平面图与它的对偶图同构，则称这个平面图是自对偶的。 (a)(a)(a) 证明：若 GGG 是自对偶的，则 q=2p−2q = 2p - 2q=2p−2 。 (b)(b)(b) 对每个 p≥4p \\geq 4p≥4 ，找出具有 ppp 个顶点的自对偶平面图。 使用知识共享 署名-相同方式共享 4.0协议发布            updated 2021-06-11 00:48:31 "},"src/part-02-graph-theory/chapter-09/9.4.html":{"url":"src/part-02-graph-theory/chapter-09/9.4.html","title":"9.4 图的顶点着色","keywords":"","body":"1. 第九章 平面图及其着色1.1. 9.4 图的顶点着色1.1.1. 31.1.2. 51.1.3. 71. 第九章 平面图及其着色 1.1. 9.4 图的顶点着色 1.1.1. 3 设 GGG 是一个有 ppp 给顶点的 ddd - 正则图。证明： χ(G)≥p/(p−d)\\chi(G) \\geq p/(p - d)χ(G)≥p/(p−d) 。 1.1.2. 5 设 GGG 是一个 (p,q)(p, q)(p,q) 图，证明： χ(G)≥p2/(p2−2q)\\chi (G) \\geq p^2 / (p^2 - 2q)χ(G)≥p2/(p2−2q) 1.1.3. 7 证明：每个哈密顿平面图都是 444 - 可着色的。 使用知识共享 署名-相同方式共享 4.0协议发布            updated 2021-06-11 00:48:31 "},"src/part-02-graph-theory/chapter-10/10.5.html":{"url":"src/part-02-graph-theory/chapter-10/10.5.html","title":"10.5 有向树与有序树","keywords":"","body":"1. 第十章 有向图1.1. 10.5 有向树与有序树1.1.1. 8.1.1.2. 9.1. 第十章 有向图 1.1. 10.5 有向树与有序树 1.1.1. 8. 令 TTT 是一个正则二元树，它有 iii 个内顶点（出度为 222 的顶点）。如果 EEE 为所有内顶点深度之和， III 为所有叶节点的深度之和，证明： I=E+2iI = E + 2iI=E+2i 证明： 设 TTT 有 ppp 个顶点，施归纳于 ppp : p=1p = 1p=1 时， I=E=i=0I = E = i = 0I=E=i=0 。 p≠2p \\neq 2p=2 。 p=3p = 3p=3 时， I=2I = 2I=2 ， E=0E = 0E=0 ， i=1i = 1i=1 ，结论成立。 假设节点数小于 ppp 时成立，往证节点数为 ppp 时也成立： 若去掉根节点及其边，产生的两棵子树节点树均小于 ppp ，符合归纳假设。设这两棵子树满足： I1=E1+2i1(1)I_1 = E_1 + 2 i_1 \\tag{1}I1​=E1​+2i1​(1) I2=E2+2i2(2)I_2 = E_2 + 2 i_2 \\tag{2}I2​=E2​+2i2​(2) 加回根节点后，两棵子树所有节点深度均加 111 。故： I=I1+I2+(p−i1−i2−1)I = I_1 + I_2 + (p - i_1 - i_2 - 1)I=I1​+I2​+(p−i1​−i2​−1) E=E1+E2+i1+i2E = E_1 + E_2 + i_1 + i_2E=E1​+E2​+i1​+i2​ i=i1+i2+1i = i_1 + i_2 + 1i=i1​+i2​+1 仅证需证明 I1+I2+(p−i1−i2−1)=E1+E2+i1+i2+2(i1+i2+1)I_1 + I_2 + (p - i_1 - i_2 - 1) = E_1 + E_2 + i_1 + i_2 + 2 (i_1 + i_2 + 1)I1​+I2​+(p−i1​−i2​−1)=E1​+E2​+i1​+i2​+2(i1​+i2​+1) 由 (1)(1)(1) 式和 (2)(2)(2) 式，化简得 p=2(i1+i2+1)+1p = 2(i_1 + i_2 + 1) + 1p=2(i1​+i2​+1)+1 ，即 p=2i+1p = 2i + 1p=2i+1 ，由于 TTT 是正则二元树，此式显然成立，故结论成立。【证毕】 1.1.2. 9. 令 TTT 是一个正则 mmm 元树，它有 iii 个内顶点（出度为 mmm 的顶点）。如果 EEE 为所有内顶点深度之和， III 为所有叶节点的深度之和，证明： I=(m−1)E+miI = (m-1)E + miI=(m−1)E+mi 使用知识共享 署名-相同方式共享 4.0协议发布            updated 2021-06-11 00:48:31 "}}